InfoTest/__init__.py
InfoTest/testclass.py
infotest-0.1.2.dist-info/METADATA
infotest-0.1.2.dist-info/WHEEL
infotest-0.1.2.dist-info/top_level.txt
infotest-0.1.2.dist-info/RECORD
