Metadata-Version: 2.1
Name: infotest
Version: 0.1.2
Summary: This is a test module to demonstrate the creation of libraries.
Home-page: https://github.com/Holodische/LibTest
Author: Eugene Bez
Author-email: holodische@gmail.com
License: UNKNOWN
Project-URL: GitHub, https://github.com/Holodische/LibTest
Keywords: files infotest
Platform: UNKNOWN
Classifier: Programming Language :: Python :: 3.10
Classifier: License :: OSI Approved :: MIT License
Classifier: Operating System :: OS Independent
Requires-Python: >=3.10
Requires-Dist: requests >=2.25.1
